bunqexport/__init__.py
bunqexport/export.py
bunqexport/tests/__init__.py
bunqexport/tests/test_exports.py
bunqexport-0.0.3.dist-info/COPYING
bunqexport-0.0.3.dist-info/LICENSE.txt
bunqexport-0.0.3.dist-info/METADATA
bunqexport-0.0.3.dist-info/WHEEL
bunqexport-0.0.3.dist-info/entry_points.txt
bunqexport-0.0.3.dist-info/top_level.txt
bunqexport-0.0.3.dist-info/RECORD
