Metadata-Version: 2.1
Name: bunqexport
Version: 0.0.3
Summary: Convert bunq payments to csv
Home-page: https://github.com/stuertz/pybunqexport
Author: Jan Stürtz
Author-email: stuertz@gmail.com
License: gpl-3.0
Keywords: open-banking sepa bunq finance api payment csv lexware finanzmanager
Platform: UNKNOWN
Classifier: Development Status :: 3 - Alpha
Classifier: Intended Audience :: End Users/Desktop
Classifier: Intended Audience :: Financial and Insurance Industry
Classifier: Topic :: Office/Business :: Financial
Classifier: License :: OSI Approved :: GNU General Public License v3 (GPLv3)
Classifier: Programming Language :: Python :: 3.6
Requires-Python: >=3.6
License-File: LICENSE.txt
License-File: COPYING
Requires-Dist: bunq-sdk
Requires-Dist: pandas
Provides-Extra: dev
Requires-Dist: autopep8 ; extra == 'dev'
Requires-Dist: flake8 ; extra == 'dev'
Requires-Dist: nose ; extra == 'dev'
Requires-Dist: pre-commit ; extra == 'dev'
Requires-Dist: pylint ; extra == 'dev'
Requires-Dist: twine ; extra == 'dev'
Requires-Dist: coverage ; extra == 'dev'
